[
    {
        "id": 0,
        "name1": "Carolina",
        "name2": "MARIN",
        "country": "Spain",
        "age": "31",
        "hand": "L",
        "world_rank": "72",
        "world_tour_rank": "-",
        "world_rank_title": "WOMEN'S SINGLES",
        "world_tour_rank_title": "NO CURRENT RANKING",
        "prize_money": "$ 1,413,204",
        "point_title": "WOMEN'S SINGLES",
        "point": "24950"
    },
    {
        "id": 1,
        "name1": "Viktor",
        "name2": "AXELSEN",
        "country": "Denmark",
        "age": "31",
        "hand": "R",
        "world_rank": "6",
        "world_tour_rank": "13",
        "world_rank_title": "MEN'S SINGLES",
        "world_tour_rank_title": "MEN'S SINGLES",
        "prize_money": "$ 2,283,160",
        "point_title": "MEN'S SINGLES",
        "point": "80340"
    },
    {
        "id": 2,
        "name1": "Chang",
        "name2": "WANG",
        "country": "China",
        "age": "24",
        "hand": "R",
        "world_rank": "3",
        "world_tour_rank": "20",
        "world_rank_title": "MEN'S DOUBLES",
        "world_tour_rank_title": "MEN'S DOUBLES",
        "prize_money": "-",
        "point_title": "MEN'S DOUBLES",
        "point": "82646"
    },
    {
        "id": 3,
        "name1": "Ha Na",
        "name2": "BAEK",
        "country": "Korea",
        "age": "24",
        "hand": "R",
        "world_rank": "3",
        "world_tour_rank": "13",
        "world_rank_title": "WOMEN'S DOUBLES",
        "world_tour_rank_title": "WOMEN'S DOUBLES",
        "prize_money": "$ 573,324",
        "point_title": "WOMEN'S DOUBLES",
        "point": "87500"
    },
    {
        "id": 4,
        "name1": "Yu Qi",
        "name2": "SHI",
        "country": "China",
        "age": "29",
        "hand": "R",
        "world_rank": "1",
        "world_tour_rank": "4",
        "world_rank_title": "MEN'S SINGLES",
        "world_tour_rank_title": "MEN'S SINGLES",
        "prize_money": "-",
        "point_title": "MEN'S SINGLES",
        "point": "100117"
    },
    {
        "id": 5,
        "name1": "Tzu Ying",
        "name2": "TAI",
        "country": "Chinese Taipei",
        "age": "30",
        "hand": "R",
        "world_rank": "104",
        "world_tour_rank": "-",
        "world_rank_title": "WOMEN'S SINGLES",
        "world_tour_rank_title": "NO CURRENT RANKING",
        "prize_money": "$ 2,375,279",
        "point_title": "WOMEN'S SINGLES",
        "point": "18300"
    },
    {
        "id": 6,
        "name1": "Kodai",
        "name2": "NARAOKA",
        "country": "Japan",
        "age": "",
        "hand": "",
        "world_rank": "8",
        "world_tour_rank": "27",
        "world_rank_title": "MEN'S SINGLES",
        "world_tour_rank_title": "MEN'S SINGLES",
        "prize_money": "-",
        "point_title": "MEN'S SINGLES",
        "point": "74584"
    },
    {
        "id": 7,
        "name1": "Ya Qiong",
        "name2": "HUANG",
        "country": "China",
        "age": "31",
        "hand": "R",
        "world_rank": "-",
        "world_tour_rank": "-",
        "world_rank_title": "NO CURRENT RANKING",
        "world_tour_rank_title": "NO CURRENT RANKING",
        "prize_money": "$ 1,556,902",
        "point_title": "MIXED DOUBLES",
        "point": "91950"
    },
    {
        "id": 8,
        "name1": "Yi Fan",
        "name2": "JIA",
        "country": "China",
        "age": "27",
        "hand": "L",
        "world_rank": "7",
        "world_tour_rank": "1",
        "world_rank_title": "WOMEN'S DOUBLES",
        "world_tour_rank_title": "WOMEN'S DOUBLES",
        "prize_money": "$ 1,047,399",
        "point_title": "WOMEN'S DOUBLES",
        "point": "72625"
    },
    {
        "id": 9,
        "name1": "Yan Zhe",
        "name2": "FENG",
        "country": "China",
        "age": "24",
        "hand": "R",
        "world_rank": "2",
        "world_tour_rank": "25",
        "world_rank_title": "MIXED DOUBLES",
        "world_tour_rank_title": "MIXED DOUBLES",
        "prize_money": "-",
        "point_title": "MIXED DOUBLES",
        "point": "93557"
    },
    {
        "id": 10,
        "name1": "Seung Jae",
        "name2": "SEO",
        "country": "Korea",
        "age": "27",
        "hand": "L",
        "world_rank": "1",
        "world_tour_rank": "",
        "world_rank_title": "MEN'S DOUBLES",
        "world_tour_rank_title": "",
        "prize_money": "$ 994,849",
        "point_title": "",
        "point": "64455"
    },
    {
        "id": 11,
        "name1": "Jonatan",
        "name2": "CHRISTIE",
        "country": "Indonesia",
        "age": "27",
        "hand": "R",
        "world_rank": "5",
        "world_tour_rank": "14",
        "world_rank_title": "MEN'S SINGLES",
        "world_tour_rank_title": "MEN'S SINGLES",
        "prize_money": "-",
        "point_title": "MEN'S SINGLES",
        "point": "80614"
    },
    {
        "id": 12,
        "name1": "Min Hyuk",
        "name2": "KANG",
        "country": "Korea",
        "age": "26",
        "hand": "R",
        "world_rank": "2",
        "world_tour_rank": "8",
        "world_rank_title": "MEN'S DOUBLES",
        "world_tour_rank_title": "MEN'S DOUBLES",
        "prize_money": "$ 242,903",
        "point_title": "MEN'S DOUBLES",
        "point": "49000"
    },
    {
        "id": 13,
        "name1": "Yu Fei",
        "name2": "CHEN",
        "country": "China",
        "age": "27",
        "hand": "R",
        "world_rank": "8",
        "world_tour_rank": "21",
        "world_rank_title": "WOMEN'S SINGLES",
        "world_tour_rank_title": "WOMEN'S SINGLES",
        "prize_money": "$ 1,478,235",
        "point_title": "WOMEN'S SINGLES",
        "point": "68435"
    },
    {
        "id": 14,
        "name1": "Si Wei",
        "name2": "ZHENG",
        "country": "China",
        "age": "28",
        "hand": "R",
        "world_rank": "-",
        "world_tour_rank": "-",
        "world_rank_title": "NO CURRENT RANKING",
        "world_tour_rank_title": "NO CURRENT RANKING",
        "prize_money": "$ 1,585,788",
        "point_title": "MIXED DOUBLES",
        "point": "91950"
    },
    {
        "id": 15,
        "name1": "Se Young",
        "name2": "AN",
        "country": "Korea",
        "age": "23",
        "hand": "R",
        "world_rank": "1",
        "world_tour_rank": "1",
        "world_rank_title": "WOMEN'S SINGLES",
        "world_tour_rank_title": "WOMEN'S SINGLES",
        "prize_money": "$ 1,773,311",
        "point_title": "WOMEN'S SINGLES",
        "point": "113320"
    },
    {
        "id": 16,
        "name1": "Wei Keng",
        "name2": "LIANG",
        "country": "China",
        "age": "24",
        "hand": "R",
        "world_rank": "3",
        "world_tour_rank": "20",
        "world_rank_title": "MEN'S DOUBLES",
        "world_tour_rank_title": "MEN'S DOUBLES",
        "prize_money": "-",
        "point_title": "MEN'S DOUBLES",
        "point": "82646"
    },
    {
        "id": 17,
        "name1": "So Hee",
        "name2": "LEE",
        "country": "Korea",
        "age": "30",
        "hand": "R",
        "world_rank": "3",
        "world_tour_rank": "13",
        "world_rank_title": "WOMEN'S DOUBLES",
        "world_tour_rank_title": "WOMEN'S DOUBLES",
        "prize_money": "$ 1,068,007",
        "point_title": "WOMEN'S DOUBLES",
        "point": "87500"
    },
    {
        "id": 18,
        "name1": "Anders",
        "name2": "ANTONSEN",
        "country": "Denmark",
        "age": "28",
        "hand": "R",
        "world_rank": "3",
        "world_tour_rank": "25",
        "world_rank_title": "MEN'S SINGLES",
        "world_tour_rank_title": "MEN'S SINGLES",
        "prize_money": "$ 982,128",
        "point_title": "MEN'S SINGLES",
        "point": "87693"
    },
    {
        "id": 19,
        "name1": "Qing Chen",
        "name2": "CHEN",
        "country": "China",
        "age": "27",
        "hand": "R",
        "world_rank": "7",
        "world_tour_rank": "77",
        "world_rank_title": "WOMEN'S DOUBLES",
        "world_tour_rank_title": "WOMEN'S DOUBLES",
        "prize_money": "$ 1,280,168",
        "point_title": "WOMEN'S DOUBLES",
        "point": "72625"
    }
]